Workbook

Sheet Inputs
A1: EduNXT agent: cost model inputs
A2: Blue = editable input · Yellow = assumption to confirm or value still to fill · Black = formula. All money in USD.
A3: AI costs: averages of 1 drafts / 1 revisions / 2 intake messages from out/benchmark/results.csv
A5: AI cost per step (Claude API; measured by `python -m edunxt benchmark`)
A6: AI cost per client message analysed (Intake Agent, Haiku) | B6: 0.0027 | C6: USD | D6: Avg of successful benchmark runs (results.csv)
A7: AI cost per draft (Research Agent, Opus + web search) | B7: 4.6774 | C7: USD | D7: Avg of successful benchmark runs (results.csv)
A8: AI cost per founder revision | B8: 0.5838 | C8: USD | D8: Avg of successful benchmark runs (results.csv)
A10: Workflow per enquiry
A11: Client messages analysed per enquiry | B11: 2 | C11: messages | D11: Benchmark cases use 2 (first enquiry + profile). Every later client message is also analysed.
A12: Share of enquiries that reach a draft | B12: 1 | D12: 100% = conservative upper bound (every enquirer completes the profile).
A13: Founder revisions per draft | B13: 1 | C13: revisions | D13: Benchmark measures 1 revision per case.
A14: Share of drafts sent while the founder's 24h window is closed | B14: 0.5 | D14: Then the agent sends the `new_case_ready` utility template first.
A15: Templates per such draft | B15: 1 | C15: templates | D15: edunxt/workflow.py `_hold`
A16: AI cost per client (derived) | B16: =IF(COUNT(B6:B8)<3,"not measured",$B$11*B6+B7+$B$13*B8) | C16: USD | D16: intake x messages + draft + revisions x revision
A18: WhatsApp messages the agent sends (counted from edunxt/workflow.py)
A19: Welcome + questionnaire to the client | B19: 1 | C19: per enquiry | D19: The only message the agent ever sends a client. On Instagram it goes out over Instagram instead.
A20: Founder notification per client message | B20: 1 | C20: per message | D20: New-enquiry / forwarded-message notes
A21: Founder messages per draft | B21: 3 | C21: per draft | D21: Summary text + University options PDF + Scholarships PDF
A22: Founder messages per revision | B22: 3 | C22: per revision | D22: Same three items, new version
A23: Other founder replies per drafted case | B23: 1 | C23: per draft | D23: e.g. the `approve` confirmation
A25: Meta pricing, Egypt (USD per delivered message)
A26: Service message (reply inside the 24h window) | B26: 0.0036 | C26: USD | D26: Meta WhatsApp Business Platform rate card, Egypt, USD, per delivered message (marketing $0.0644 from 1 Jan 2026; utility/authentication $0.0036, July 2026 card). From 1 Oct 2026 service messages are billed at the utility rate after 1,000 free per business phone number per month, and utility templates inside the 24h window are billable. developers.facebook.com/docs/whatsapp/pricing. Checked 3 Oct 2026 via secondary sources; confirm in WhatsApp Manager.
A27: Utility template (founder `new_case_ready`) | B27: 0.0036 | C27: USD | D27: Volume tiers can lower this by up to 25%; ignored here.
A28: Free service messages per number per month | B28: 1000 | C28: messages | D28: From 1 Oct 2026; resets monthly, no rollover.
A29: VAT added to Meta's invoice | B29: 0.14 | D29: Egyptian VAT 14%. Set 0% if it doesn't apply to your billing entity.
A30: Instagram message fee | B30: 0 | C30: USD | D30: Instagram Messaging API (Graph API): no per-message fee. Replies only within 24h of the user's last message; the HUMAN_AGENT tag (7 days) needs its own App Review and may not be used for automated messages.
A31: Marketing template (reference only; the agent sends none) | B31: 0.0644 | C31: USD | D31: Not used in the model.
A33: Fixed monthly costs
A34: Hosting | B34: 0 | C34: USD / month | D34: PoC runs on a laptop ($0). A small cloud VM is roughly $5-20/month.
A35: WhatsApp Cloud API number / access | B35: 0 | C35: USD / month | D35: No platform fee from Meta for Cloud API.
A37: EduNXT business figures
A38: Enquiry to enrolment rate | B38: 0.3 | D38: From EduNXT
A39: Commission per student (share of annual university fees) | B39: 0.1 | D39: From EduNXT
A40: Average annual university fees | B40: 10000 | C40: USD / year | D40: ASSUMPTION for illustration; replace with EduNXT's average.
A41: Founder time to build one list today | B41: 1.5 | C41: hours | D41: From EduNXT: 1-2 hours (midpoint)
A42: Founder time to review an agent draft | B42: 0.25 | C42: hours | D42: ASSUMPTION: 15 minutes to read, tweak and approve.
A43: Current enquiries per month | B43: 15 | C43: enquiries | D43: From EduNXT (WhatsApp + Instagram)

Sheet Monthly cost
A1: Monthly running cost by number of new enquiries
A2: =IF(COUNT(Inputs!B6:B8)<3,"AI cost not yet measured: AI columns show $0 until Inputs!B6:B8 are filled from the benchmark.","AI cost per client: "&TEXT(Inputs!$B$16,"$0.00"))
A4: WhatsApp: client enquires on WhatsApp; agent replies on WhatsApp; founders review on WhatsApp
A5: Enquiries / month | B5: Drafts | C5: Client msgs analysed | D5: WhatsApp service msgs | E5: Billable service msgs | F5: Utility templates | G5: Meta fees (USD) | H5: AI cost (USD) | I5: Fixed (USD) | J5: Total / month (USD) | K5: Per enquiry (USD) | L5: Per enrolled student (USD)
A6: 25 | B6: =A6*Inputs!$B$12 | C6: =A6*Inputs!$B$11 | D6: =A6*Inputs!$B$19+C6*Inputs!$B$20+B6*(Inputs!$B$21+Inputs!$B$13*Inputs!$B$22+Inputs!$B$23) | E6: =MAX(0,D6-Inputs!$B$28) | F6: =B6*Inputs!$B$14*Inputs!$B$15 | G6: =(E6*Inputs!$B$26+F6*Inputs!$B$27)*(1+Inputs!$B$29)+0 | H6: =C6*N(Inputs!$B$6)+B6*(N(Inputs!$B$7)+Inputs!$B$13*N(Inputs!$B$8)) | I6: =Inputs!$B$34+Inputs!$B$35 | J6: =G6+H6+I6 | K6: =IF(A6>0,J6/A6,0) | L6: =IF(A6*Inputs!$B$38>0,J6/(A6*Inputs!$B$38),0)
A7: 50 | B7: =A7*Inputs!$B$12 | C7: =A7*Inputs!$B$11 | D7: =A7*Inputs!$B$19+C7*Inputs!$B$20+B7*(Inputs!$B$21+Inputs!$B$13*Inputs!$B$22+Inputs!$B$23) | E7: =MAX(0,D7-Inputs!$B$28) | F7: =B7*Inputs!$B$14*Inputs!$B$15 | G7: =(E7*Inputs!$B$26+F7*Inputs!$B$27)*(1+Inputs!$B$29)+0 | H7: =C7*N(Inputs!$B$6)+B7*(N(Inputs!$B$7)+Inputs!$B$13*N(Inputs!$B$8)) | I7: =Inputs!$B$34+Inputs!$B$35 | J7: =G7+H7+I7 | K7: =IF(A7>0,J7/A7,0) | L7: =IF(A7*Inputs!$B$38>0,J7/(A7*Inputs!$B$38),0)
A8: 100 | B8: =A8*Inputs!$B$12 | C8: =A8*Inputs!$B$11 | D8: =A8*Inputs!$B$19+C8*Inputs!$B$20+B8*(Inputs!$B$21+Inputs!$B$13*Inputs!$B$22+Inputs!$B$23) | E8: =MAX(0,D8-Inputs!$B$28) | F8: =B8*Inputs!$B$14*Inputs!$B$15 | G8: =(E8*Inputs!$B$26+F8*Inputs!$B$27)*(1+Inputs!$B$29)+0 | H8: =C8*N(Inputs!$B$6)+B8*(N(Inputs!$B$7)+Inputs!$B$13*N(Inputs!$B$8)) | I8: =Inputs!$B$34+Inputs!$B$35 | J8: =G8+H8+I8 | K8: =IF(A8>0,J8/A8,0) | L8: =IF(A8*Inputs!$B$38>0,J8/(A8*Inputs!$B$38),0)
A9: 150 | B9: =A9*Inputs!$B$12 | C9: =A9*Inputs!$B$11 | D9: =A9*Inputs!$B$19+C9*Inputs!$B$20+B9*(Inputs!$B$21+Inputs!$B$13*Inputs!$B$22+Inputs!$B$23) | E9: =MAX(0,D9-Inputs!$B$28) | F9: =B9*Inputs!$B$14*Inputs!$B$15 | G9: =(E9*Inputs!$B$26+F9*Inputs!$B$27)*(1+Inputs!$B$29)+0 | H9: =C9*N(Inputs!$B$6)+B9*(N(Inputs!$B$7)+Inputs!$B$13*N(Inputs!$B$8)) | I9: =Inputs!$B$34+Inputs!$B$35 | J9: =G9+H9+I9 | K9: =IF(A9>0,J9/A9,0) | L9: =IF(A9*Inputs!$B$38>0,J9/(A9*Inputs!$B$38),0)
A10: 200 | B10: =A10*Inputs!$B$12 | C10: =A10*Inputs!$B$11 | D10: =A10*Inputs!$B$19+C10*Inputs!$B$20+B10*(Inputs!$B$21+Inputs!$B$13*Inputs!$B$22+Inputs!$B$23) | E10: =MAX(0,D10-Inputs!$B$28) | F10: =B10*Inputs!$B$14*Inputs!$B$15 | G10: =(E10*Inputs!$B$26+F10*Inputs!$B$27)*(1+Inputs!$B$29)+0 | H10: =C10*N(Inputs!$B$6)+B10*(N(Inputs!$B$7)+Inputs!$B$13*N(Inputs!$B$8)) | I10: =Inputs!$B$34+Inputs!$B$35 | J10: =G10+H10+I10 | K10: =IF(A10>0,J10/A10,0) | L10: =IF(A10*Inputs!$B$38>0,J10/(A10*Inputs!$B$38),0)
A11: 250 | B11: =A11*Inputs!$B$12 | C11: =A11*Inputs!$B$11 | D11: =A11*Inputs!$B$19+C11*Inputs!$B$20+B11*(Inputs!$B$21+Inputs!$B$13*Inputs!$B$22+Inputs!$B$23) | E11: =MAX(0,D11-Inputs!$B$28) | F11: =B11*Inputs!$B$14*Inputs!$B$15 | G11: =(E11*Inputs!$B$26+F11*Inputs!$B$27)*(1+Inputs!$B$29)+0 | H11: =C11*N(Inputs!$B$6)+B11*(N(Inputs!$B$7)+Inputs!$B$13*N(Inputs!$B$8)) | I11: =Inputs!$B$34+Inputs!$B$35 | J11: =G11+H11+I11 | K11: =IF(A11>0,J11/A11,0) | L11: =IF(A11*Inputs!$B$38>0,J11/(A11*Inputs!$B$38),0)
A12: 300 | B12: =A12*Inputs!$B$12 | C12: =A12*Inputs!$B$11 | D12: =A12*Inputs!$B$19+C12*Inputs!$B$20+B12*(Inputs!$B$21+Inputs!$B$13*Inputs!$B$22+Inputs!$B$23) | E12: =MAX(0,D12-Inputs!$B$28) | F12: =B12*Inputs!$B$14*Inputs!$B$15 | G12: =(E12*Inputs!$B$26+F12*Inputs!$B$27)*(1+Inputs!$B$29)+0 | H12: =C12*N(Inputs!$B$6)+B12*(N(Inputs!$B$7)+Inputs!$B$13*N(Inputs!$B$8)) | I12: =Inputs!$B$34+Inputs!$B$35 | J12: =G12+H12+I12 | K12: =IF(A12>0,J12/A12,0) | L12: =IF(A12*Inputs!$B$38>0,J12/(A12*Inputs!$B$38),0)
A13: 400 | B13: =A13*Inputs!$B$12 | C13: =A13*Inputs!$B$11 | D13: =A13*Inputs!$B$19+C13*Inputs!$B$20+B13*(Inputs!$B$21+Inputs!$B$13*Inputs!$B$22+Inputs!$B$23) | E13: =MAX(0,D13-Inputs!$B$28) | F13: =B13*Inputs!$B$14*Inputs!$B$15 | G13: =(E13*Inputs!$B$26+F13*Inputs!$B$27)*(1+Inputs!$B$29)+0 | H13: =C13*N(Inputs!$B$6)+B13*(N(Inputs!$B$7)+Inputs!$B$13*N(Inputs!$B$8)) | I13: =Inputs!$B$34+Inputs!$B$35 | J13: =G13+H13+I13 | K13: =IF(A13>0,J13/A13,0) | L13: =IF(A13*Inputs!$B$38>0,J13/(A13*Inputs!$B$38),0)
A14: 500 | B14: =A14*Inputs!$B$12 | C14: =A14*Inputs!$B$11 | D14: =A14*Inputs!$B$19+C14*Inputs!$B$20+B14*(Inputs!$B$21+Inputs!$B$13*Inputs!$B$22+Inputs!$B$23) | E14: =MAX(0,D14-Inputs!$B$28) | F14: =B14*Inputs!$B$14*Inputs!$B$15 | G14: =(E14*Inputs!$B$26+F14*Inputs!$B$27)*(1+Inputs!$B$29)+0 | H14: =C14*N(Inputs!$B$6)+B14*(N(Inputs!$B$7)+Inputs!$B$13*N(Inputs!$B$8)) | I14: =Inputs!$B$34+Inputs!$B$35 | J14: =G14+H14+I14 | K14: =IF(A14>0,J14/A14,0) | L14: =IF(A14*Inputs!$B$38>0,J14/(A14*Inputs!$B$38),0)
A17: Instagram: client enquires by Instagram DM; welcome sent over the Instagram Messaging API (free); founders still review on WhatsApp
A18: Enquiries / month | B18: Drafts | C18: Client msgs analysed | D18: WhatsApp service msgs | E18: Billable service msgs | F18: Utility templates | G18: Meta fees (USD) | H18: AI cost (USD) | I18: Fixed (USD) | J18: Total / month (USD) | K18: Per enquiry (USD) | L18: Per enrolled student (USD)
A19: 25 | B19: =A19*Inputs!$B$12 | C19: =A19*Inputs!$B$11 | D19: =0+C19*Inputs!$B$20+B19*(Inputs!$B$21+Inputs!$B$13*Inputs!$B$22+Inputs!$B$23) | E19: =MAX(0,D19-Inputs!$B$28) | F19: =B19*Inputs!$B$14*Inputs!$B$15 | G19: =(E19*Inputs!$B$26+F19*Inputs!$B$27)*(1+Inputs!$B$29)+A19*Inputs!$B$19*Inputs!$B$30 | H19: =C19*N(Inputs!$B$6)+B19*(N(Inputs!$B$7)+Inputs!$B$13*N(Inputs!$B$8)) | I19: =Inputs!$B$34+Inputs!$B$35 | J19: =G19+H19+I19 | K19: =IF(A19>0,J19/A19,0) | L19: =IF(A19*Inputs!$B$38>0,J19/(A19*Inputs!$B$38),0)
A20: 50 | B20: =A20*Inputs!$B$12 | C20: =A20*Inputs!$B$11 | D20: =0+C20*Inputs!$B$20+B20*(Inputs!$B$21+Inputs!$B$13*Inputs!$B$22+Inputs!$B$23) | E20: =MAX(0,D20-Inputs!$B$28) | F20: =B20*Inputs!$B$14*Inputs!$B$15 | G20: =(E20*Inputs!$B$26+F20*Inputs!$B$27)*(1+Inputs!$B$29)+A20*Inputs!$B$19*Inputs!$B$30 | H20: =C20*N(Inputs!$B$6)+B20*(N(Inputs!$B$7)+Inputs!$B$13*N(Inputs!$B$8)) | I20: =Inputs!$B$34+Inputs!$B$35 | J20: =G20+H20+I20 | K20: =IF(A20>0,J20/A20,0) | L20: =IF(A20*Inputs!$B$38>0,J20/(A20*Inputs!$B$38),0)
A21: 100 | B21: =A21*Inputs!$B$12 | C21: =A21*Inputs!$B$11 | D21: =0+C21*Inputs!$B$20+B21*(Inputs!$B$21+Inputs!$B$13*Inputs!$B$22+Inputs!$B$23) | E21: =MAX(0,D21-Inputs!$B$28) | F21: =B21*Inputs!$B$14*Inputs!$B$15 | G21: =(E21*Inputs!$B$26+F21*Inputs!$B$27)*(1+Inputs!$B$29)+A21*Inputs!$B$19*Inputs!$B$30 | H21: =C21*N(Inputs!$B$6)+B21*(N(Inputs!$B$7)+Inputs!$B$13*N(Inputs!$B$8)) | I21: =Inputs!$B$34+Inputs!$B$35 | J21: =G21+H21+I21 | K21: =IF(A21>0,J21/A21,0) | L21: =IF(A21*Inputs!$B$38>0,J21/(A21*Inputs!$B$38),0)
A22: 150 | B22: =A22*Inputs!$B$12 | C22: =A22*Inputs!$B$11 | D22: =0+C22*Inputs!$B$20+B22*(Inputs!$B$21+Inputs!$B$13*Inputs!$B$22+Inputs!$B$23) | E22: =MAX(0,D22-Inputs!$B$28) | F22: =B22*Inputs!$B$14*Inputs!$B$15 | G22: =(E22*Inputs!$B$26+F22*Inputs!$B$27)*(1+Inputs!$B$29)+A22*Inputs!$B$19*Inputs!$B$30 | H22: =C22*N(Inputs!$B$6)+B22*(N(Inputs!$B$7)+Inputs!$B$13*N(Inputs!$B$8)) | I22: =Inputs!$B$34+Inputs!$B$35 | J22: =G22+H22+I22 | K22: =IF(A22>0,J22/A22,0) | L22: =IF(A22*Inputs!$B$38>0,J22/(A22*Inputs!$B$38),0)
A23: 200 | B23: =A23*Inputs!$B$12 | C23: =A23*Inputs!$B$11 | D23: =0+C23*Inputs!$B$20+B23*(Inputs!$B$21+Inputs!$B$13*Inputs!$B$22+Inputs!$B$23) | E23: =MAX(0,D23-Inputs!$B$28) | F23: =B23*Inputs!$B$14*Inputs!$B$15 | G23: =(E23*Inputs!$B$26+F23*Inputs!$B$27)*(1+Inputs!$B$29)+A23*Inputs!$B$19*Inputs!$B$30 | H23: =C23*N(Inputs!$B$6)+B23*(N(Inputs!$B$7)+Inputs!$B$13*N(Inputs!$B$8)) | I23: =Inputs!$B$34+Inputs!$B$35 | J23: =G23+H23+I23 | K23: =IF(A23>0,J23/A23,0) | L23: =IF(A23*Inputs!$B$38>0,J23/(A23*Inputs!$B$38),0)
A24: 250 | B24: =A24*Inputs!$B$12 | C24: =A24*Inputs!$B$11 | D24: =0+C24*Inputs!$B$20+B24*(Inputs!$B$21+Inputs!$B$13*Inputs!$B$22+Inputs!$B$23) | E24: =MAX(0,D24-Inputs!$B$28) | F24: =B24*Inputs!$B$14*Inputs!$B$15 | G24: =(E24*Inputs!$B$26+F24*Inputs!$B$27)*(1+Inputs!$B$29)+A24*Inputs!$B$19*Inputs!$B$30 | H24: =C24*N(Inputs!$B$6)+B24*(N(Inputs!$B$7)+Inputs!$B$13*N(Inputs!$B$8)) | I24: =Inputs!$B$34+Inputs!$B$35 | J24: =G24+H24+I24 | K24: =IF(A24>0,J24/A24,0) | L24: =IF(A24*Inputs!$B$38>0,J24/(A24*Inputs!$B$38),0)
A25: 300 | B25: =A25*Inputs!$B$12 | C25: =A25*Inputs!$B$11 | D25: =0+C25*Inputs!$B$20+B25*(Inputs!$B$21+Inputs!$B$13*Inputs!$B$22+Inputs!$B$23) | E25: =MAX(0,D25-Inputs!$B$28) | F25: =B25*Inputs!$B$14*Inputs!$B$15 | G25: =(E25*Inputs!$B$26+F25*Inputs!$B$27)*(1+Inputs!$B$29)+A25*Inputs!$B$19*Inputs!$B$30 | H25: =C25*N(Inputs!$B$6)+B25*(N(Inputs!$B$7)+Inputs!$B$13*N(Inputs!$B$8)) | I25: =Inputs!$B$34+Inputs!$B$35 | J25: =G25+H25+I25 | K25: =IF(A25>0,J25/A25,0) | L25: =IF(A25*Inputs!$B$38>0,J25/(A25*Inputs!$B$38),0)
A26: 400 | B26: =A26*Inputs!$B$12 | C26: =A26*Inputs!$B$11 | D26: =0+C26*Inputs!$B$20+B26*(Inputs!$B$21+Inputs!$B$13*Inputs!$B$22+Inputs!$B$23) | E26: =MAX(0,D26-Inputs!$B$28) | F26: =B26*Inputs!$B$14*Inputs!$B$15 | G26: =(E26*Inputs!$B$26+F26*Inputs!$B$27)*(1+Inputs!$B$29)+A26*Inputs!$B$19*Inputs!$B$30 | H26: =C26*N(Inputs!$B$6)+B26*(N(Inputs!$B$7)+Inputs!$B$13*N(Inputs!$B$8)) | I26: =Inputs!$B$34+Inputs!$B$35 | J26: =G26+H26+I26 | K26: =IF(A26>0,J26/A26,0) | L26: =IF(A26*Inputs!$B$38>0,J26/(A26*Inputs!$B$38),0)
A27: 500 | B27: =A27*Inputs!$B$12 | C27: =A27*Inputs!$B$11 | D27: =0+C27*Inputs!$B$20+B27*(Inputs!$B$21+Inputs!$B$13*Inputs!$B$22+Inputs!$B$23) | E27: =MAX(0,D27-Inputs!$B$28) | F27: =B27*Inputs!$B$14*Inputs!$B$15 | G27: =(E27*Inputs!$B$26+F27*Inputs!$B$27)*(1+Inputs!$B$29)+A27*Inputs!$B$19*Inputs!$B$30 | H27: =C27*N(Inputs!$B$6)+B27*(N(Inputs!$B$7)+Inputs!$B$13*N(Inputs!$B$8)) | I27: =Inputs!$B$34+Inputs!$B$35 | J27: =G27+H27+I27 | K27: =IF(A27>0,J27/A27,0) | L27: =IF(A27*Inputs!$B$38>0,J27/(A27*Inputs!$B$38),0)
A29: WhatsApp service messages = welcome (WhatsApp only) + one founder note per client message + founder messages per draft and revision.
A30: Only service messages above the free 1,000 per number per month are billed, so at today's volume Meta fees are close to $0.
A31: Instagram: the agent's single client message is inside Instagram's 24h window, so the window rule doesn't limit it. Integrating Instagram needs Meta App Review (instagram_business_manage_messages); until then founders start Instagram cases with `new ...` on WhatsApp.
A32: Volumes in column A are editable.

Sheet Value
A1: What the cost buys: time saved and commission at stake (WhatsApp table)
A2: Commission uses the ASSUMED average annual fees on Inputs; replace it before quoting revenue.
A4: Enquiries / month | B4: Enrolled students | C4: Commission / month (USD) | D4: Agent cost / month (USD) | E4: Agent cost as % of commission | F4: Founder hours on lists today | G4: Founder hours with agent | H4: Founder hours saved / month
A5: =Inputs!$B$43 | B5: =A5*Inputs!$B$38 | C5: =B5*Inputs!$B$40*Inputs!$B$39 | D5: =N(Inputs!$B$16)*A5*Inputs!$B$12 | E5: =IF(C5>0,D5/C5,0) | F5: =A5*Inputs!$B$12*Inputs!$B$41 | G5: =A5*Inputs!$B$12*Inputs!$B$42 | H5: =F5-G5 | I5: ← EduNXT today
A6: ='Monthly cost'!A6 | B6: =A6*Inputs!$B$38 | C6: =B6*Inputs!$B$40*Inputs!$B$39 | D6: ='Monthly cost'!J6 | E6: =IF(C6>0,D6/C6,0) | F6: =A6*Inputs!$B$12*Inputs!$B$41 | G6: =A6*Inputs!$B$12*Inputs!$B$42 | H6: =F6-G6
A7: ='Monthly cost'!A7 | B7: =A7*Inputs!$B$38 | C7: =B7*Inputs!$B$40*Inputs!$B$39 | D7: ='Monthly cost'!J7 | E7: =IF(C7>0,D7/C7,0) | F7: =A7*Inputs!$B$12*Inputs!$B$41 | G7: =A7*Inputs!$B$12*Inputs!$B$42 | H7: =F7-G7
A8: ='Monthly cost'!A8 | B8: =A8*Inputs!$B$38 | C8: =B8*Inputs!$B$40*Inputs!$B$39 | D8: ='Monthly cost'!J8 | E8: =IF(C8>0,D8/C8,0) | F8: =A8*Inputs!$B$12*Inputs!$B$41 | G8: =A8*Inputs!$B$12*Inputs!$B$42 | H8: =F8-G8
A9: ='Monthly cost'!A9 | B9: =A9*Inputs!$B$38 | C9: =B9*Inputs!$B$40*Inputs!$B$39 | D9: ='Monthly cost'!J9 | E9: =IF(C9>0,D9/C9,0) | F9: =A9*Inputs!$B$12*Inputs!$B$41 | G9: =A9*Inputs!$B$12*Inputs!$B$42 | H9: =F9-G9
A10: ='Monthly cost'!A10 | B10: =A10*Inputs!$B$38 | C10: =B10*Inputs!$B$40*Inputs!$B$39 | D10: ='Monthly cost'!J10 | E10: =IF(C10>0,D10/C10,0) | F10: =A10*Inputs!$B$12*Inputs!$B$41 | G10: =A10*Inputs!$B$12*Inputs!$B$42 | H10: =F10-G10
A11: ='Monthly cost'!A11 | B11: =A11*Inputs!$B$38 | C11: =B11*Inputs!$B$40*Inputs!$B$39 | D11: ='Monthly cost'!J11 | E11: =IF(C11>0,D11/C11,0) | F11: =A11*Inputs!$B$12*Inputs!$B$41 | G11: =A11*Inputs!$B$12*Inputs!$B$42 | H11: =F11-G11
A12: ='Monthly cost'!A12 | B12: =A12*Inputs!$B$38 | C12: =B12*Inputs!$B$40*Inputs!$B$39 | D12: ='Monthly cost'!J12 | E12: =IF(C12>0,D12/C12,0) | F12: =A12*Inputs!$B$12*Inputs!$B$41 | G12: =A12*Inputs!$B$12*Inputs!$B$42 | H12: =F12-G12
A13: ='Monthly cost'!A13 | B13: =A13*Inputs!$B$38 | C13: =B13*Inputs!$B$40*Inputs!$B$39 | D13: ='Monthly cost'!J13 | E13: =IF(C13>0,D13/C13,0) | F13: =A13*Inputs!$B$12*Inputs!$B$41 | G13: =A13*Inputs!$B$12*Inputs!$B$42 | H13: =F13-G13
A14: ='Monthly cost'!A14 | B14: =A14*Inputs!$B$38 | C14: =B14*Inputs!$B$40*Inputs!$B$39 | D14: ='Monthly cost'!J14 | E14: =IF(C14>0,D14/C14,0) | F14: =A14*Inputs!$B$12*Inputs!$B$41 | G14: =A14*Inputs!$B$12*Inputs!$B$42 | H14: =F14-G14

Sheet Sensitivity
A1: Total monthly cost (WhatsApp) if the AI cost per client were...
A2: Use this before the benchmark has run, or to see how much the AI cost matters. Meta fees and fixed costs come from 'Monthly cost'.
A4: Enquiries / month | B4: 0.5 | C4: 1 | D4: 2 | E4: 3 | F4: 5
A5: ='Monthly cost'!A6 | B5: ='Monthly cost'!G6+'Monthly cost'!I6+A5*Inputs!$B$12*B$4 | C5: ='Monthly cost'!G6+'Monthly cost'!I6+A5*Inputs!$B$12*C$4 | D5: ='Monthly cost'!G6+'Monthly cost'!I6+A5*Inputs!$B$12*D$4 | E5: ='Monthly cost'!G6+'Monthly cost'!I6+A5*Inputs!$B$12*E$4 | F5: ='Monthly cost'!G6+'Monthly cost'!I6+A5*Inputs!$B$12*F$4
A6: ='Monthly cost'!A7 | B6: ='Monthly cost'!G7+'Monthly cost'!I7+A6*Inputs!$B$12*B$4 | C6: ='Monthly cost'!G7+'Monthly cost'!I7+A6*Inputs!$B$12*C$4 | D6: ='Monthly cost'!G7+'Monthly cost'!I7+A6*Inputs!$B$12*D$4 | E6: ='Monthly cost'!G7+'Monthly cost'!I7+A6*Inputs!$B$12*E$4 | F6: ='Monthly cost'!G7+'Monthly cost'!I7+A6*Inputs!$B$12*F$4
A7: ='Monthly cost'!A8 | B7: ='Monthly cost'!G8+'Monthly cost'!I8+A7*Inputs!$B$12*B$4 | C7: ='Monthly cost'!G8+'Monthly cost'!I8+A7*Inputs!$B$12*C$4 | D7: ='Monthly cost'!G8+'Monthly cost'!I8+A7*Inputs!$B$12*D$4 | E7: ='Monthly cost'!G8+'Monthly cost'!I8+A7*Inputs!$B$12*E$4 | F7: ='Monthly cost'!G8+'Monthly cost'!I8+A7*Inputs!$B$12*F$4
A8: ='Monthly cost'!A9 | B8: ='Monthly cost'!G9+'Monthly cost'!I9+A8*Inputs!$B$12*B$4 | C8: ='Monthly cost'!G9+'Monthly cost'!I9+A8*Inputs!$B$12*C$4 | D8: ='Monthly cost'!G9+'Monthly cost'!I9+A8*Inputs!$B$12*D$4 | E8: ='Monthly cost'!G9+'Monthly cost'!I9+A8*Inputs!$B$12*E$4 | F8: ='Monthly cost'!G9+'Monthly cost'!I9+A8*Inputs!$B$12*F$4
A9: ='Monthly cost'!A10 | B9: ='Monthly cost'!G10+'Monthly cost'!I10+A9*Inputs!$B$12*B$4 | C9: ='Monthly cost'!G10+'Monthly cost'!I10+A9*Inputs!$B$12*C$4 | D9: ='Monthly cost'!G10+'Monthly cost'!I10+A9*Inputs!$B$12*D$4 | E9: ='Monthly cost'!G10+'Monthly cost'!I10+A9*Inputs!$B$12*E$4 | F9: ='Monthly cost'!G10+'Monthly cost'!I10+A9*Inputs!$B$12*F$4
A10: ='Monthly cost'!A11 | B10: ='Monthly cost'!G11+'Monthly cost'!I11+A10*Inputs!$B$12*B$4 | C10: ='Monthly cost'!G11+'Monthly cost'!I11+A10*Inputs!$B$12*C$4 | D10: ='Monthly cost'!G11+'Monthly cost'!I11+A10*Inputs!$B$12*D$4 | E10: ='Monthly cost'!G11+'Monthly cost'!I11+A10*Inputs!$B$12*E$4 | F10: ='Monthly cost'!G11+'Monthly cost'!I11+A10*Inputs!$B$12*F$4
A11: ='Monthly cost'!A12 | B11: ='Monthly cost'!G12+'Monthly cost'!I12+A11*Inputs!$B$12*B$4 | C11: ='Monthly cost'!G12+'Monthly cost'!I12+A11*Inputs!$B$12*C$4 | D11: ='Monthly cost'!G12+'Monthly cost'!I12+A11*Inputs!$B$12*D$4 | E11: ='Monthly cost'!G12+'Monthly cost'!I12+A11*Inputs!$B$12*E$4 | F11: ='Monthly cost'!G12+'Monthly cost'!I12+A11*Inputs!$B$12*F$4
A12: ='Monthly cost'!A13 | B12: ='Monthly cost'!G13+'Monthly cost'!I13+A12*Inputs!$B$12*B$4 | C12: ='Monthly cost'!G13+'Monthly cost'!I13+A12*Inputs!$B$12*C$4 | D12: ='Monthly cost'!G13+'Monthly cost'!I13+A12*Inputs!$B$12*D$4 | E12: ='Monthly cost'!G13+'Monthly cost'!I13+A12*Inputs!$B$12*E$4 | F12: ='Monthly cost'!G13+'Monthly cost'!I13+A12*Inputs!$B$12*F$4
A13: ='Monthly cost'!A14 | B13: ='Monthly cost'!G14+'Monthly cost'!I14+A13*Inputs!$B$12*B$4 | C13: ='Monthly cost'!G14+'Monthly cost'!I14+A13*Inputs!$B$12*C$4 | D13: ='Monthly cost'!G14+'Monthly cost'!I14+A13*Inputs!$B$12*D$4 | E13: ='Monthly cost'!G14+'Monthly cost'!I14+A13*Inputs!$B$12*E$4 | F13: ='Monthly cost'!G14+'Monthly cost'!I14+A13*Inputs!$B$12*F$4

Sheet Sources
A1: Sources and notes
A2: WhatsApp pricing (Egypt): Meta WhatsApp Business Platform rate card, Egypt, USD, per delivered message (marketing $0.0644 from 1 Jan 2026; utility/authentication $0.0036, July 2026 card). From 1 Oct 2026 service messages are billed at the utility rate after 1,000 free per business phone number per month, and utility templates inside the 24h window are billable. developers.facebook.com/docs/whatsapp/pricing. Checked 3 Oct 2026 via secondary sources; confirm in WhatsApp Manager.
A3: Instagram Messaging API: Instagram Messaging API (Graph API): no per-message fee. Replies only within 24h of the user's last message; the HUMAN_AGENT tag (7 days) needs its own App Review and may not be used for automated messages.
A4: Claude API prices used by the cost meter (edunxt/agents/llm.py): Opus 5.5 $4 / $20 per million input / output tokens; Haiku 4.5 $1 / $5; web search $10 per 1,000.
A5: Message counts per case: edunxt/workflow.py (_handle_client, _deliver, _hold).
A6: Business figures (15 enquiries/month, 30% enrolment, 10% commission, 1-2 h per list, 12-24 h reply time): EduNXT founders.
A7: Generated by scripts/build_cost_model.py. Re-run it after a benchmark to refresh the AI-cost inputs.
